log0/__init__.py
log0-1.0.1.dist-info/DESCRIPTION.rst
log0-1.0.1.dist-info/METADATA
log0-1.0.1.dist-info/RECORD
log0-1.0.1.dist-info/WHEEL
log0-1.0.1.dist-info/metadata.json
log0-1.0.1.dist-info/top_level.txt
