Metadata-Version: 2.0
Name: log0
Version: 1.0.1
Summary: Simplified Python Logging
Home-page: https://github.com/metachris/log0
Author: Chris Hager
Author-email: chris@linuxuser.at
License: MIT license
Keywords: log0
Platform: UNKNOWN
Classifier: Development Status :: 2 - Pre-Alpha
Classifier: Intended Audience :: Developers
Classifier: License :: OSI Approved :: MIT License
Classifier: Natural Language :: English
Classifier: Programming Language :: Python :: 2
Classifier: Programming Language :: Python :: 2.6
Classifier: Programming Language :: Python :: 2.7
Classifier: Programming Language :: Python :: 3
Classifier: Programming Language :: Python :: 3.3
Classifier: Programming Language :: Python :: 3.4
Classifier: Programming Language :: Python :: 3.5
